notifyourself/__init__.py
notifyourself/notifyourself.py
notifyourself-0.1.0.dist-info/LICENSE
notifyourself-0.1.0.dist-info/METADATA
notifyourself-0.1.0.dist-info/WHEEL
notifyourself-0.1.0.dist-info/entry_points.txt
notifyourself-0.1.0.dist-info/top_level.txt
notifyourself-0.1.0.dist-info/RECORD
