Metadata-Version: 2.1
Name: notifyourself
Version: 0.1.0
Summary: Send a notification to your mobile device
Home-page: https://github.com/wchresta/NotifYourselfCLI
Author: Wanja Chresta
Author-email: wanja.hs@chrummibei.ch
License: LICENSE
Project-URL: Source Code, https://github.com/wchresta/NotifYourselfCLI
Project-URL: Issues, https://github.com/wchresta/NotifYourselfCLI/issues
Platform: UNKNOWN
Classifier: Programming Language :: Python :: 2
Classifier: Programming Language :: Python :: 3
Classifier: Intended Audience :: End Users/Desktop
Classifier: Intended Audience :: Science/Research
Classifier: Development Status :: 4 - Beta
Classifier: Environment :: Console
Classifier: License :: OSI Approved :: GNU General Public License v3 or later (GPLv3+)
Classifier: Operating System :: OS Independent
Classifier: Topic :: Utilities
Requires-Python: >=2
Requires-Dist: requests (>=2.0)
